pyflirts/__init__.py
pyflirts/cs_flirts.py
pyflirts/en_flirts.py
pyflirts/errors.py
pyflirts/es_flirts.py
pyflirts/fr_flirts.py
pyflirts/he_flirts.py
pyflirts/hi_flirts.py
pyflirts/ja_flirts.py
pyflirts/ko_flirts.py
pyflirts/pa_flirts.py
pyflirts/pyflirts.py
pyflirts/ru_flirts.py
pyflirts-0.0.1.dist-info/LICENSE
pyflirts-0.0.1.dist-info/METADATA
pyflirts-0.0.1.dist-info/WHEEL
pyflirts-0.0.1.dist-info/top_level.txt
pyflirts-0.0.1.dist-info/RECORD
