Metadata-Version: 2.1
Name: pyflirts
Version: 0.0.1
Summary: one line flirt lines for programmers ( flirt lines as a service )
Home-page: https://github.com/pyflirts/pyflirts
Author: Shiva Mishra
Author-email: pyflirts@gmail.com
Classifier: Programming Language :: Python :: 3
Classifier: License :: OSI Approved :: MIT License
Classifier: Operating System :: OS Independent
Requires-Python: >=3.6
License-File: LICENSE
